mango_mdconverter/__init__.py
mango_mdconverter/md2dict.py
mango_mdconverter-0.0.10.dist-info/licenses/LICENSE
mango_mdconverter-0.0.10.dist-info/METADATA
mango_mdconverter-0.0.10.dist-info/WHEEL
mango_mdconverter-0.0.10.dist-info/top_level.txt
mango_mdconverter-0.0.10.dist-info/RECORD
