Metadata-Version: 2.4
Name: mango-mdconverter
Version: 0.0.10
Summary: ManGO metadata conversion
Author-email: Mariana Montes <mariana.montes@kuleuven.be>, Paul Borgermans <paul.borgermans@kuleuven.be>
License: MIT License
Project-URL: repository, https://github.com/kuleuven/mango-mdconverter
Requires-Python: >=3.8
License-File: LICENSE
Requires-Dist: mango-mdschema>=1.0.3
Requires-Dist: python-irodsclient>=2.2,>=3.0
Provides-Extra: dev
Dynamic: license-file
